vercel/functions/__init__.py
vercel/functions/_context.py
vercel/functions/headers.py
vercel/functions/purge.py
vercel/functions/cache/__init__.py
vercel/functions/cache/build_client.py
vercel/functions/cache/in_memory_cache.py
vercel/functions/cache/index.py
vercel/functions/cache/types.py
vercel/oidc/__init__.py
vercel/oidc/credentials.py
vercel/oidc/token.py
vercel/oidc/token_util.py
vercel_core-0.0.1.dist-info/METADATA
vercel_core-0.0.1.dist-info/WHEEL
vercel_core-0.0.1.dist-info/top_level.txt
vercel_core-0.0.1.dist-info/RECORD
