Metadata-Version: 2.4
Name: vercel-core
Version: 0.0.1
Summary: Python SDK for Vercel
License: MIT
Requires-Python: >=3.9
Requires-Dist: httpx>=0.27.0
Requires-Dist: pydantic>=2.7.0
Requires-Dist: anyio>=4.0.0
Requires-Dist: python-dotenv
Provides-Extra: dev
Requires-Dist: ruff>=0.5.0; extra == "dev"
Requires-Dist: pytest>=7.0.0; extra == "dev"
Requires-Dist: build; extra == "dev"
Requires-Dist: twine; extra == "dev"
